s3empty/__init__.py
s3empty/logger.py
s3empty-2.0.0.dist-info/METADATA
s3empty-2.0.0.dist-info/WHEEL
s3empty-2.0.0.dist-info/entry_points.txt
s3empty-2.0.0.dist-info/licenses/LICENSE
s3empty-2.0.0.dist-info/RECORD
