Metadata-Version: 2.4
Name: s3empty
Version: 2.0.0
Summary: Python CLI for convenient emptying of S3 bucket
License: Apache-2.0
License-File: LICENSE
Keywords: s3empty,aws,bucket,empty,s3
Author: Cliffano Subagio
Author-email: cliffano@gmail.com
Requires-Python: >=3.10,<4.0
Classifier: License :: OSI Approved :: Apache Software License
Classifier: Operating System :: OS Independent
Classifier: Programming Language :: Python :: 3
Classifier: Programming Language :: Python :: 3.10
Classifier: Programming Language :: Python :: 3.11
Classifier: Programming Language :: Python :: 3.12
Classifier: Programming Language :: Python :: 3.13
Classifier: Programming Language :: Python :: 3.14
Requires-Dist: boto3 (>=1.42.25,<1.43.0)
Requires-Dist: cfgrw (>=1.0.0,<1.1.0)
Requires-Dist: click (>=8.3.1,<8.4.0)
Requires-Dist: conflog (>=2.1.0,<2.2.0)
Project-URL: Documentation, https://github.com/cliffano/s3empty
Project-URL: Homepage, https://github.com/cliffano/s3empty
Project-URL: Repository, https://github.com/cliffano/s3empty
